calciumlang/__init__.py
calciumlang/address.py
calciumlang/block.py
calciumlang/block_result.py
calciumlang/element.py
calciumlang/environment.py
calciumlang/error.py
calciumlang/index.py
calciumlang/keyword.py
calciumlang/label.py
calciumlang/namespace.py
calciumlang/parser.py
calciumlang/runtime.py
calciumlang/command/__init__.py
calciumlang/command/assign.py
calciumlang/command/class_stmt.py
calciumlang/command/command.py
calciumlang/command/expr_stmt.py
calciumlang/command/function.py
calciumlang/command/ifs.py
calciumlang/command/import_stmt.py
calciumlang/command/loop.py
calciumlang/command/pass_stmt.py
calciumlang/expression/__init__.py
calciumlang/expression/assignable.py
calciumlang/expression/call.py
calciumlang/expression/operator.py
calciumlang/tools/__init__.py
calciumlang/tools/converter.py
calciumlang-0.0.5.dist-info/METADATA
calciumlang-0.0.5.dist-info/WHEEL
calciumlang-0.0.5.dist-info/licenses/LICENSE
calciumlang-0.0.5.dist-info/RECORD
