Metadata-Version: 2.4
Name: calciumlang
Version: 0.0.5
Summary: A Calcium language interpreter
Project-URL: Homepage, https://github.com/0xCAF2/calciumlang
Author-email: 0xCAF2 <roki@0xcaf2.dev>
License-File: LICENSE
Keywords: calcium,interpreter,json
Classifier: License :: OSI Approved :: MIT License
Classifier: Operating System :: OS Independent
Classifier: Programming Language :: Python :: 3
Requires-Python: >=3.9
